{
  "type": "Feature",
  "geometry": {
    "type": "Point",
    "coordinates": [
      121.615953,
      25.059905
    ]
  },
  "properties": {
    "編號": "B10",
    "站名": "南港軟體園區",
    "name": "Nangang Software Park",
    "路線編號": "1",
    "線名": "文湖線",
    "郵遞區號": 11568,
    "地址": "台北市南港區經貿二路183號",
    "緯度": 25.059905,
    "經度": 121.615953
  }
}