{
  "type": "Feature",
  "geometry": {
    "type": "Point",
    "coordinates": [
      121.555592,
      25.084853
    ]
  },
  "properties": {
    "編號": "B2",
    "站名": "劍南路",
    "name": "Jiannan Rd.",
    "路線編號": "1",
    "線名": "文湖線",
    "郵遞區號": 10464,
    "地址": "台北市中山區北安路798號",
    "緯度": 25.084853,
    "經度": 121.555592
  }
}