{
  "type": "Feature",
  "geometry": {
    "type": "Point",
    "coordinates": [
      121.575081,
      25.080028
    ]
  },
  "properties": {
    "編號": "B4",
    "站名": "港墘",
    "name": "Gangqian",
    "路線編號": "1",
    "線名": "文湖線",
    "郵遞區號": 11446,
    "地址": "台北市內湖區內湖路一段663號",
    "緯度": 25.080028,
    "經度": 121.575081
  }
}