{
  "type": "Feature",
  "geometry": {
    "type": "Point",
    "coordinates": [
      121.594408,
      25.083661
    ]
  },
  "properties": {
    "編號": "B6",
    "站名": "內湖",
    "name": "Neihu",
    "路線編號": "1",
    "線名": "文湖線",
    "郵遞區號": 11489,
    "地址": "台北市內湖區成功路四段186號",
    "緯度": 25.083661,
    "經度": 121.594408
  }
}