{
  "type": "Feature",
  "geometry": {
    "type": "Point",
    "coordinates": [
      121.607158,
      25.072701
    ]
  },
  "properties": {
    "編號": "B8",
    "站名": "葫洲",
    "name": "Huzhou",
    "路線編號": "1",
    "線名": "文湖線",
    "郵遞區號": 11486,
    "地址": "台北市內湖區康寧路三段16號",
    "緯度": 25.072701,
    "經度": 121.607158
  }
}