{
  "type": "Feature",
  "geometry": {
    "type": "Point",
    "coordinates": [
      121.558152,
      24.999386
    ]
  },
  "properties": {
    "編號": "BR10",
    "站名": "萬芳醫院",
    "name": "Wanfang Hospital",
    "路線編號": "1",
    "線名": "文湖線",
    "郵遞區號": 11696,
    "地址": "台北市文山區興隆路三段113號",
    "緯度": 24.999386,
    "經度": 121.558152
  }
}