{
  "type": "Feature",
  "geometry": {
    "type": "Point",
    "coordinates": [
      121.568102,
      24.998585
    ]
  },
  "properties": {
    "編號": "BR11",
    "站名": "萬芳社區",
    "name": "Wanfang Community",
    "路線編號": "1",
    "線名": "文湖線",
    "郵遞區號": 11653,
    "地址": "台北市文山區萬芳路60號",
    "緯度": 24.998585,
    "經度": 121.568102
  }
}