{
  "type": "Feature",
  "geometry": {
    "type": "Point",
    "coordinates": [
      121.553115,
      25.023777
    ]
  },
  "properties": {
    "編號": "BR7",
    "站名": "六張犁",
    "name": "Liuzhangli",
    "路線編號": "1",
    "線名": "文湖線",
    "郵遞區號": 10674,
    "地址": "台北市大安區和平東路三段168號",
    "緯度": 25.023777,
    "經度": 121.553115
  }
}