{
  "type": "Feature",
  "geometry": {
    "type": "Point",
    "coordinates": [
      121.557107,
      25.005475
    ]
  },
  "properties": {
    "編號": "BR9",
    "站名": "辛亥",
    "name": "Xinhai",
    "路線編號": "1",
    "線名": "文湖線",
    "郵遞區號": 11694,
    "地址": "台北市文山區辛亥路四段128號",
    "緯度": 25.005475,
    "經度": 121.557107
  }
}