{
  "type": "Feature",
  "geometry": {
    "type": "Point",
    "coordinates": [
      121.51932,
      25.062905
    ]
  },
  "properties": {
    "編號": "R16",
    "站名": "民權西路",
    "name": "MinquanW. Rd.",
    "路線編號": "2",
    "線名": "淡水信義線",
    "郵遞區號": 10365,
    "地址": "台北市大同區民權西路72號",
    "緯度": 25.062905,
    "經度": 121.51932
  }
}