{
  "type": "Feature",
  "geometry": {
    "type": "Point",
    "coordinates": [
      121.515559,
      25.114523
    ]
  },
  "properties": {
    "編號": "R23",
    "站名": "石牌",
    "name": "Shipai",
    "路線編號": "2",
    "線名": "淡水信義線",
    "郵遞區號": 11271,
    "地址": "台北市北投區石牌路一段200號",
    "緯度": 25.114523,
    "經度": 121.515559
  }
}