{
  "type": "Feature",
  "geometry": {
    "type": "Point",
    "coordinates": [
      121.47341,
      25.130969
    ]
  },
  "properties": {
    "編號": "R29",
    "站名": "忠義",
    "name": "Zhongyi",
    "路線編號": "2",
    "線名": "淡水信義線",
    "郵遞區號": 11257,
    "地址": "台北市北投區中央北路四段301號",
    "緯度": 25.130969,
    "經度": 121.47341
  }
}