{
  "type": "Feature",
  "geometry": {
    "type": "Point",
    "coordinates": [
      121.54131,
      24.967393
    ]
  },
  "properties": {
    "編號": "G2",
    "站名": "新店區公所",
    "name": "Xindian District Office",
    "路線編號": "3",
    "線名": "松山新店線",
    "郵遞區號": 23147,
    "地址": "新北市新店區北新路一段295號",
    "緯度": 24.967393,
    "經度": 121.54131
  }
}