{
  "type": "Feature",
  "geometry": {
    "type": "Point",
    "coordinates": [
      121.541352,
      24.982899
    ]
  },
  "properties": {
    "編號": "G4",
    "站名": "大坪林",
    "name": "Dapinglin",
    "路線編號": "3",
    "線名": "松山新店線",
    "郵遞區號": 23143,
    "地址": "新北市新店區北新路三段190號",
    "緯度": 24.982899,
    "經度": 121.541352
  }
}