{
  "type": "Feature",
  "geometry": {
    "type": "Point",
    "coordinates": [
      121.565228,
      25.041171
    ]
  },
  "properties": {
    "編號": "BL13",
    "站名": "市政府",
    "name": "Taipei City Hall",
    "路線編號": "5",
    "線名": "板南線",
    "郵遞區號": 11071,
    "地址": "台北市信義區忠孝東路五段2號",
    "緯度": 25.041171,
    "經度": 121.565228
  }
}