{
  "type": "Feature",
  "geometry": {
    "type": "Point",
    "coordinates": [
      121.576293,
      25.040859
    ]
  },
  "properties": {
    "編號": "BL14",
    "站名": "永春",
    "name": "Yongchun",
    "路線編號": "5",
    "線名": "板南線",
    "郵遞區號": 11061,
    "地址": "台北市信義區忠孝東路五段455號",
    "緯度": 25.040859,
    "經度": 121.576293
  }
}