{
  "type": "Feature",
  "geometry": {
    "type": "Point",
    "coordinates": [
      121.468361,
      25.023738
    ]
  },
  "properties": {
    "編號": "BL3",
    "站名": "新埔",
    "name": "Xinpu",
    "路線編號": "5",
    "線名": "板南線",
    "郵遞區號": 22047,
    "地址": "新北市板橋區民生路三段2號B1",
    "緯度": 25.023738,
    "經度": 121.468361
  }
}