{
  "type": "Feature",
  "geometry": {
    "type": "Point",
    "coordinates": [
      121.47239,
      25.03001
    ]
  },
  "properties": {
    "編號": "BL4",
    "站名": "江子翠",
    "name": "Jiangzicui",
    "路線編號": "5",
    "線名": "板南線",
    "郵遞區號": 22044,
    "地址": "新北市板橋區文化路二段296號B1",
    "緯度": 25.03001,
    "經度": 121.47239
  }
}