{
  "type": "Feature",
  "geometry": {
    "type": "Point",
    "coordinates": [
      121.532905,
      25.042356
    ]
  },
  "properties": {
    "編號": "BL9",
    "站名": "忠孝新生",
    "name": "Zhongxiao Xinsheng",
    "路線編號": "5",
    "線名": "板南線",
    "郵遞區號": 10652,
    "地址": "台北市大安區新生南路一段67號",
    "緯度": 25.042356,
    "經度": 121.532905
  }
}